[
    {
        "title": "Закотвяне",
        "description": "Първото нещо, което преценявате, влияе върху начина, по който възприемате всичко след него.",
        "link": "anchoring",
        "english": "Anchoring"
    },
    {
        "title": "Необратими загуби",
        "description": "Продължавате с нещо само защото вече сте вложили ресурси в него, въпреки че това може да не е най_доброто решение.",
        "link": "sunk_cost_fallacy",
        "english": "Sunk Cost Fallacy"
    },
    {
        "title": "Евристика на наличността",
        "description": "Предпочитате информация, която е леснодостъпна в съзнанието ви, вместо да оцените всички факти обективно.",
        "link": "availability_heuristic",
        "english": "Availability Heuristic"
    },
    {
        "title": "Проклятие на знанието",
        "description": "Трудно ви е да си представите какво е да не знаете нещо, което вече сте научили.",
        "link": "curse_of_knowledge",
        "english": "Curse of Knowledge"
    },
    {
        "title": "Склонност за потвърждаване",
        "description": "Склонни сте да търсите и вярвате само на информация, която подкрепя вашите съществуващи убеждения.",
        "link": "confirmation_bias",
        "english": "Confirmation Bias"
    },
    {
        "title": "Ефект на Дънинг-Крюгер",
        "description": "Хората с малко познания често надценяват компетентността си, докато експертите могат да я подценяват.",
        "link": "dunning_kruger_effect",
        "english": "Dunning-Kruger Effect"
    },
    {
        "title": "Пристрастие към вярванията",
        "description": "Склонни сте да приемате аргументи за верни или неверни въз основа на това дали заключението им съвпада с вашите съществуващи убеждения, а не на тяхната логическа стойност.",
        "link": "belief_bias",
        "english": "Belief Bias"
    },
    {
        "title": "Уклон към себичност",
        "description": "Приписвате успехите си на собствените си способности и усилия, а неуспехите – на външни фактори, извън вашия контрол.",
        "link": "self_serving_bias",
        "english": "Self-Serving Bias"
    },
    {
        "title": "Обратен ефект",
        "description": "Когато ви представят доказателства, които противоречат на вашите убеждения, те могат да ви направят още по-убедени в първоначалната си позиция, вместо да я промените.",
        "link": "backfire_effect",
        "english": "Backfire Effect"
    },
    {
        "title": "Ефект на Барнум",
        "description": "Приписвате лична значимост на неясни или общи твърдения, като хороскопи.",
        "link": "barnum_effect",
        "english": "Barnum Effect"
    },
    {
        "title": "Групово мислене",
        "description": "Склонни сте да се съгласявате с групата, за да избегнете конфликти, дори ако не сте напълно съгласни.",
        "link": "groupthink",
        "english": "Groupthink"
    },
    {
        "title": "Негативен уклон",
        "description": "Отдавате повече значение на негативната информация, отколкото на позитивната.",
        "link": "negativity_bias",
        "english": "Negativity Bias"
    },
    {
        "title": "Черногледство",
        "description": "Смятате, че миналото е било по-добро, отколкото реално е било, и че бъдещето ще бъде по-лошо.",
        "link": "declinism",
        "english": "Declinism"
    },
    {
        "title": "Ефект на рамкирането",
        "description": "Решенията ви зависят от това как е представена информацията, а не само от фактите.",
        "link": "framing-effect",
        "english": "Framing Effect"
    },
    {
        "title": "Фундаментална атрибутивна грешка",
        "description": "Склонни сте да обяснявате действията на другите с техния характер, а не с обстоятелствата.",
        "link": "fundamental_attribution_error",
        "english": "Fundamental Attribution Error"
    },
    {
        "title": "Ефект на ореола",
        "description": "Ако харесвате един аспект от някого или нещо, сте склонни да надценявате и другите му характеристики.",
        "link": "halo_effect",
        "english": "Halo Effect"
    },
    {
        "title": "Оптимистичен уклон",
        "description": "Склонни сте да вярвате, че положителните събития са по-вероятни за вас, отколкото за другите.",
        "link": "optimism_bias",
        "english": "Optimism Bias"
    },
    {
        "title": "Песимистичен уклон",
        "description": "Склонни сте да надценявате вероятността от негативни събития.",
        "link": "pessimism_bias",
        "english": "Pessimism Bias"
    },
    {
        "title": "Хипотеза за справедливия свят",
        "description": "Вярвате, че хората получават това, което заслужават, и че светът е справедлив.",
        "link": "just_world_hypothesis",
        "english": "Just-World Hypothesis"
    },
    {
        "title": "Пристрастие към групата",
        "description": "Предпочитате членове на собствената си група пред тези от други групи.",
        "link": "in_group_bias",
        "english": "In-Group Bias"
    },
    {
        "title": "Плацебо ефект",
        "description": "Изпитвате възприемано подобрение в състоянието си поради вярата в ефективността на неактивно лечение.",
        "link": "placebo_effect",
        "english": "Placebo Effect"
    },
    {
        "title": "Ефект на страничния наблюдател",
        "description": "Хората са по-малко склонни да окажат помощ, ако има и други свидетели.",
        "link": "bystander_effect",
        "english": "Bystander Effect"
    },
    {
        "title": "Реактивно съпротивление",
        "description": "Когато се чувствате ограничени в избора си, сте склонни да правите обратното на очакваното.",
        "link": "reactance",
        "english": "Reactance"
    },
    {
        "title": "Ефект на прожектора",
        "description": "Надценявате колко много другите забелязват и обръщат внимание на вашия външен вид или действия.",
        "link": "spotlight_effect",
        "english": "Spotlight Effect"
    }
]
